{
  "list_url": "https://www.deu.ac.kr/www/gra-notice.do?mode=list",
  "page_no": 15,
  "count": 13,
  "items": [
    {
      "article_no": "82127",
      "title_hint": "2026학년도 1학기 출석인정 신청 및 처리안내",
      "detail_url": "https://www.deu.ac.kr/www/gra-notice.do?mode=view&articleNo=82127&article.offset=140&articleLimit=10",
      "published_at_hint": "2026-03-03",
      "row_text": "공지 2026학년도 1학기 출석인정 신청 및 처리안내 학사지원팀 2026-03-03 297"
    },
    {
      "article_no": "80310",
      "title_hint": "다전공 안내 가이드(2026)",
      "detail_url": "https://www.deu.ac.kr/www/gra-notice.do?mode=view&articleNo=80310&article.offset=140&articleLimit=10",
      "published_at_hint": "2026-01-21",
      "row_text": "공지 다전공 안내 가이드(2026) 학사지원팀 2026-01-21 535"
    },
    {
      "article_no": "80309",
      "title_hint": "학사정보 종합안내 가이드(2026)",
      "detail_url": "https://www.deu.ac.kr/www/gra-notice.do?mode=view&articleNo=80309&article.offset=140&articleLimit=10",
      "published_at_hint": "2026-01-21",
      "row_text": "공지 학사정보 종합안내 가이드(2026) 학사지원팀 2026-01-21 1504"
    },
    {
      "article_no": "65463",
      "title_hint": "2024학년도 2학기 복학안내",
      "detail_url": "https://www.deu.ac.kr/www/gra-notice.do?mode=view&articleNo=65463&article.offset=140&articleLimit=10",
      "published_at_hint": "2024-06-27",
      "row_text": "824 2024학년도 2학기 복학안내 학사지원팀 2024-06-27 2794"
    },
    {
      "article_no": "65457",
      "title_hint": "모집 중지학과 소속학생(복수전공 포함)의 졸업논문 제출 관련사항 안내(불문, 독문, 사학, 철학상담심리, 수학, 물리, 화학, 분자생물, 생명응용)(~2024.7.12까지 제출)",
      "detail_url": "https://www.deu.ac.kr/www/gra-notice.do?mode=view&articleNo=65457&article.offset=140&articleLimit=10",
      "published_at_hint": "2024-06-24",
      "row_text": "823 모집 중지학과 소속학생(복수전공 포함)의 졸업논문 제출 관련사항 안내(불문, 독문, 사학, 철학상담심리, 수학, 물리, 화학, 분자생물, 생명응용)(~2024.7.12까지 제출) 학사지원팀 2024-06-24 511"
    },
    {
      "article_no": "65266",
      "title_hint": "2024학년도 2학기 휴학안내",
      "detail_url": "https://www.deu.ac.kr/www/gra-notice.do?mode=view&articleNo=65266&article.offset=140&articleLimit=10",
      "published_at_hint": "2024-06-13",
      "row_text": "822 2024학년도 2학기 휴학안내 학사지원팀 2024-06-13 5051"
    },
    {
      "article_no": "65458",
      "title_hint": "학칙 개정안 공고(제2024-3호)",
      "detail_url": "https://www.deu.ac.kr/www/gra-notice.do?mode=view&articleNo=65458&article.offset=140&articleLimit=10",
      "published_at_hint": "2024-06-10",
      "row_text": "821 학칙 개정안 공고(제2024-3호) 학사지원팀 2024-06-10 602"
    },
    {
      "article_no": "65265",
      "title_hint": "2024-하계계절수업 2차 수강신청 및 현금등록 안내",
      "detail_url": "https://www.deu.ac.kr/www/gra-notice.do?mode=view&articleNo=65265&article.offset=140&articleLimit=10",
      "published_at_hint": "2024-06-07",
      "row_text": "820 2024-하계계절수업 2차 수강신청 및 현금등록 안내 학사지원팀 2024-06-07 1610"
    },
    {
      "article_no": "65456",
      "title_hint": "2024학년도 1학기 성적 공고 및 정정 일정 안내",
      "detail_url": "https://www.deu.ac.kr/www/gra-notice.do?mode=view&articleNo=65456&article.offset=140&articleLimit=10",
      "published_at_hint": "2024-05-29",
      "row_text": "819 2024학년도 1학기 성적 공고 및 정정 일정 안내 학사지원팀 2024-05-29 4270"
    },
    {
      "article_no": "64791",
      "title_hint": "2024학년도 1학기 출석 및 공결 인정 신청 접수 및 처리 마감일자 안내",
      "detail_url": "https://www.deu.ac.kr/www/gra-notice.do?mode=view&articleNo=64791&article.offset=140&articleLimit=10",
      "published_at_hint": "2024-05-28",
      "row_text": "818 2024학년도 1학기 출석 및 공결 인정 신청 접수 및 처리 마감일자 안내 학사지원팀 2024-05-28 3722"
    },
    {
      "article_no": "64705",
      "title_hint": "2024학년도 2학기 학석사 연계과정 신청안내",
      "detail_url": "https://www.deu.ac.kr/www/gra-notice.do?mode=view&articleNo=64705&article.offset=140&articleLimit=10",
      "published_at_hint": "2024-05-23",
      "row_text": "817 2024학년도 2학기 학석사 연계과정 신청안내 학사지원팀 2024-05-23 607"
    },
    {
      "article_no": "64704",
      "title_hint": "2024-하계계절수업 폐강 및 수강정정 안내",
      "detail_url": "https://www.deu.ac.kr/www/gra-notice.do?mode=view&articleNo=64704&article.offset=140&articleLimit=10",
      "published_at_hint": "2024-05-20",
      "row_text": "816 2024-하계계절수업 폐강 및 수강정정 안내 학사지원팀 2024-05-20 1047"
    },
    {
      "article_no": "64703",
      "title_hint": "2024학년도 1학기 코로나(인플루엔자 포함) 방역조치 변경에 따른 출석인정일자 변경 안내",
      "detail_url": "https://www.deu.ac.kr/www/gra-notice.do?mode=view&articleNo=64703&article.offset=140&articleLimit=10",
      "published_at_hint": "2024-05-17",
      "row_text": "815 2024학년도 1학기 코로나(인플루엔자 포함) 방역조치 변경에 따른 출석인정일자 변경 안내 학사지원팀 2024-05-17 357"
    }
  ]
}